Workbook

Sheet Principales Metricas
A1: Calculos | B1: =Datos!B1 -> 0
A2: Precio Actual | B2: =Datos!B3 -> 0
A4: Partida: Perdidas y Ganancias | D4: Partida: Balance General | G4: Partida: Flujo de Caja
A6: Ingresos | B6: =IFERROR(VLOOKUP("Total Revenues*",Datos!$A:$K,COLUMN(B1),FALSE),"0") -> 0 | D6: Efectivo y equivalentes al efectivo | E6: =IFERROR(VLOOKUP("Cash And Equivalents*",Datos!$A:$B,COLUMN(B1),FALSE),"0") -> 0 | G6: Dividendos | H6: =IFERROR(ABS(VLOOKUP("Common & Preferred Stock Dividend Paid",Datos!$A:$B,COLUMN(B1),FALSE)),"0") -> 0
A7: EBITDA | B7: =B9-B8 -> 0 | D7: Valores negociables | E7: =IFERROR(VLOOKUP("Total Cash And Short Term Investments*",Datos!$A:$B,COLUMN(B1),FALSE)-E6,"0") -> 0 | G7: Recompras | H7: =IFERROR(ABS(VLOOKUP("Repurchase of Common Stock*",Datos!$A:$B,COLUMN(B1),FALSE)),"0") -> 0
A8: Depreciacion y Amortizacion | B8: =IFERROR(-VLOOKUP("Depreciation*",Datos!$A:$B,COLUMN(B1),FALSE)-IFERROR(VLOOKUP("Amortization of Goodwill and Intangible Assets*",Datos!$A:$B,COLUMN(B1),FALSE),"0"),"0") -> 0 | D8: Deuda a corto plazo | E8: =IFERROR(VLOOKUP("Short-term Borrowings*",Datos!$A:$B,COLUMN(B1),FALSE),"0")+IFERROR(VLOOKUP("Current Portion of Long-Term Debt*",Datos!$A:$K,COLUMN(B1),FALSE),"0")+IFERROR(VLOOKUP("Finance Division Debt Current*",Datos!$A:$K,COLUMN(B1),FALSE),"0") -> 0 | G8: Amortizacion neta de deuda | H8: =IFERROR(ABS(VLOOKUP("Total Debt Repaid*",Datos!$A:$B,COLUMN(B1),FALSE))-VLOOKUP("Total Debt Issued*",Datos!$A:$B,COLUMN(B1),FALSE),0) -> 0
A9: EBIT | B9: =IFERROR(VLOOKUP("Operating Income*",Datos!$A:$K,COLUMN(B1),FALSE),"0") -> 0 | D9: Deuda a largo plazo | E9: =IFERROR(VLOOKUP("Long-term Borrowings*",Datos!$A:$B,COLUMN(B1),FALSE),"0")+IFERROR(VLOOKUP("Long-Term Debt*",Datos!$A:$B,COLUMN(B1),FALSE),"0")+IFERROR(VLOOKUP("Finance Division Debt Non Current*",Datos!$A:$B,COLUMN(B1),FALSE),"0") -> 0 | G9: Capital Expenditure | H9: =IFERROR(VLOOKUP("Capital Expenditure*",Datos!$A:$B,COLUMN(B1),FALSE),"0") -> 0
A10: Intereses (Salida) | B10: =IFERROR(VLOOKUP("Interest Expense*",Datos!$A:$K,COLUMN(B1),FALSE),"0") -> 0 | D10: Pasivos por arrendamientos operativos corrientes | E10: =IFERROR(VLOOKUP("Current Portion of Capital Lease Obligations*",Datos!$A:$B,COLUMN(B1),FALSE),"0") -> 0 | G10: Sale (Purchase) of Intangible assets | H10: =IFERROR(VLOOKUP("Sale (Purchase) of Intangible assets",Datos!$A:$B,COLUMN(B1),FALSE),"0") -> 0
A11: Intereses (Entrada) | B11: =IFERROR(VLOOKUP("Interes And Investment Income",Datos!$A:$K,COLUMN(B1),FALSE),"0") -> 0 | D11: Pasivos por arrendamientos operativos no corrientes | E11: =IFERROR(VLOOKUP("Capital Leases*",Datos!$A:$B,COLUMN(B1),FALSE),"0") -> 0 | G11: Sale of Property, Plant, and Equipment | H11: =IFERROR(VLOOKUP("Sale of Property, Plan and Equipment",Datos!$A:$B,COLUMN(B1),FALSE),"0") -> 0
A12: Total Intereses | B12: =B10+B11 -> 0 | D12: Patrimonio neto / Capital propio | E12: =IFERROR(VLOOKUP("Total Equity*",Datos!$A:$B,COLUMN(B1),FALSE),"0") -> 0 | G12: CapEx Neto | H12: =SUM(H9:H11) -> 0
A13: EBT | B13: =B9+B12 -> 0 | D13: Deuda Neta | E13: =(E8+E9)-(E6+E7) -> 0 | G13: Depreciacion y Amortizacion | H13: =IFERROR(VLOOKUP("Depreciation & Amortization*",Datos!$A:$B,COLUMN(B1),FALSE),"0") -> 0
A14: Impuestos | B14: =IFERROR(VLOOKUP("Income Tax Expense*",Datos!$A:$B,COLUMN(B1),FALSE),"0") -> 0 | G14: CapEx Mantenimiento | H14: =IF(ABS(H12)<H13,H12,-H13)+H11 -> 0
A15: Beneficio Neto | B15: =B13+B14 -> 0 | G15: Inventorio | H15: =IFERROR(VLOOKUP("Inventory*",Datos!$A:$B,COLUMN(B1),FALSE),"0") -> 0
A16: EPS Diluido | B16: =B15/B17 -> #DIV/0! | G16: Accounts Receivable | H16: =IFERROR(VLOOKUP("Accounts Receivable*",Datos!$A:$B,COLUMN(B1),FALSE),"0") -> 0
A17: Total Acciones Diluidas | B17: =IFERROR(VLOOKUP("*Diluted Shares Outstanding*",Datos!$A:$B,COLUMN(B1),FALSE),"0") -> 0 | G17: Accounts Payable | H17: =IFERROR(VLOOKUP("Accounts Payable*",Datos!$A:$B,COLUMN(B1),FALSE),"0") -> 0
G18: Unearned Revenue | H18: =IFERROR(VLOOKUP("Unearned Revenue Current*",Datos!$A:$B,COLUMN(B1),FALSE),"0")+IFERROR(VLOOKUP("Unearned Revenue Non Current*",Datos!$A:$B,COLUMN(B1),FALSE),"0") -> 0
A19: Margen EBITDA | B19: =B7/B6 -> #DIV/0! | G19: Working Capital - WC | H19: =H15+H16-H17-H18 -> 0
A20: Marge EBIT | B20: =B9/B6 -> #DIV/0! | G20: Free Cash Flow | H20: =SUM(B7,H14,B12,B14) -> 0
A21: Margen Neto | B21: =B15/B6 -> #DIV/0! | G21: Margen FCF | H21: =H20/B6 -> #DIV/0!
G22: FCF por accion | H22: =H20/B17 -> #DIV/0!
G23: Cambio Neto en Efectivo | H23: =IFERROR(VLOOKUP("Net Change in Cash*",Datos!$A:$B,COLUMN(B1),FALSE),"0") -> 0
A26: Metricas apalancamiento | D26: Principales Ratios de valoracion | G26: Precio Objetivo
A28: Deuda Neta / EBITDA | B28: =E13/B7 -> #DIV/0! | D28: Capitalizacion de Mercado | E28: =IFERROR((VLOOKUP("PRECIO DE ACCION ANUAL",Datos!$A:$B,COLUMN(B1),FALSE)*B17),"") -> 0 | G28: Per ex Cash | H28: =IF(B2<>"",IFERROR(IF(--E13<0,(B15*E32-E13),IF(--E13>0,B15*E32))/B17,""),"")
A29: Deuda Neta / FCF (Free Cash Flow) | B29: =E13/H20 -> #DIV/0! | D29: Enterprise Value | E29: =SUM(E28,E13) -> 0 | G29: EV/FCF | H29: =IF(B2<>"",IFERROR(((H20*E33)-E13)/B17,""),"")
A30: WC / Ventas | B30: =H19/B6 -> #DIV/0! | G30: EV/EBITDA | H30: =IF(B2<>"",IFERROR(((B7*E31)-E13)/B17,""),"")
D31: EV/EBITDA | E31: =E29/B7 -> #DIV/0! | G31: EV/EBIT | H31: =IF(B2<>"",IFERROR(((B9*E34)-E13)/B17,""),"")
D32: PER | E32: =E28/B15 -> #DIV/0!
D33: EV/FCF | E33: =E29/H20 -> #DIV/0!
D34: EV/EBIT | E34: =E29/B9 -> #DIV/0!
A35: Metricas de rentabilidad
A37: EBIT x (1-t) | B37: =IFERROR(B9*(1-IFERROR((ABS(B14)/B13),"")),"")
A38: Capital Invertido | B38: =SUM(E8:E12)-E7 -> 0
A39: CapEx Expansion | B39: =H12-H14 -> 0
A40: Adquisiciones | B40: =IFERROR(VLOOKUP("Cash Acquisitions*",Datos!$A:$B,COLUMN(B1),FALSE),"0") -> 0
A41: Inversion en crecimiento | B41: =ABS(SUM(B39:B40)) -> 0
A43: ROE | B43: =B15/E12 -> #DIV/0!
A44: ROIC | B44: =B37/B38 -> #VALUE!
A45: Tasa de reinversion | B45: =IF(H20>0,IFERROR(B41/H20,""),"")

Sheet Datos
A1: FECHA
A2: PRECIO DE ACCION ANUAL
A3: PRECIO DE ACCION ACTUAL
A4: Total Revenues
A5: Operating Income
A6: Interest Expense
A7: Interes And Investment Income
A8: Income Tax Expense
A9: Weight Average Diluted Shares Outstanding
A10: Minority Interest
A11: Cash and Equivalents
A12: Total Cash And Short Term Investments
... A36: Net Change in Cash
